liana/__init__.py
liana/_constants.py
liana/_docs.py
liana/_logging.py
liana/method/__init__.py
liana/method/_pipe_utils/__init__.py
liana/method/_pipe_utils/_aggregate.py
liana/method/_pipe_utils/_common.py
liana/method/_pipe_utils/_get_mean_perms.py
liana/method/_pipe_utils/_pre.py
liana/method/fun/__init__.py
liana/method/fun/_causalnet.py
liana/method/fun/_estimate_metalinks.py
liana/method/sc/_Method.py
liana/method/sc/__init__.py
liana/method/sc/_cellchat.py
liana/method/sc/_cellphonedb.py
liana/method/sc/_connectome.py
liana/method/sc/_geometric_mean.py
liana/method/sc/_liana_pipe.py
liana/method/sc/_logfc.py
liana/method/sc/_natmi.py
liana/method/sc/_rank_aggregate.py
liana/method/sc/_scseqcomm.py
liana/method/sc/_singlecellsignalr.py
liana/method/sp/__init__.py
liana/method/sp/_compute_global_specificity.py
liana/method/sp/_inflow.py
liana/method/sp/_utils.py
liana/method/sp/_bivariate/__init__.py
liana/method/sp/_bivariate/_global_functions.py
liana/method/sp/_bivariate/_local_functions.py
liana/method/sp/_bivariate/_spatial_bivariate.py
liana/method/sp/_misty/_Misty.py
liana/method/sp/_misty/__init__.py
liana/method/sp/_misty/_misty_constructs.py
liana/method/sp/_misty/_single_view_models.py
liana/multi/__init__.py
liana/multi/_nmf.py
liana/multi/df_to_lr.py
liana/multi/to_mudata.py
liana/multi/to_tensor_c2c.py
liana/plotting/__init__.py
liana/plotting/_circle_plot.py
liana/plotting/_common.py
liana/plotting/_connectivity_plot.py
liana/plotting/_dotplot.py
liana/plotting/_feature_by_group.py
liana/plotting/_misty_plots.py
liana/plotting/_tileplot.py
liana/resource/__init__.py
liana/resource/_orthology.py
liana/resource/_reassemble_complexes.py
liana/resource/_resource_utils.py
liana/resource/get_metalinks.py
liana/resource/omni_resource.csv
liana/resource/select_resource.py
liana/testing/__init__.py
liana/testing/_sample_anndata.py
liana/testing/_sample_dea.py
liana/testing/_sample_lrs.py
liana/testing/_sample_misty.py
liana/testing/_sample_resource.py
liana-1.7.1.dist-info/METADATA
liana-1.7.1.dist-info/WHEEL
liana-1.7.1.dist-info/licenses/LICENSE
liana-1.7.1.dist-info/RECORD
