Metadata-Version: 2.4
Name: liana
Version: 1.7.1
Summary: LIANA+: a one-stop-shop framework for cell-cell communication
Project-URL: Documentation, https://liana.readthedocs.io/
Project-URL: Homepage, https://liana-py.readthedocs.io
Project-URL: Source, https://github.com/saezlab/liana-py
Author: Daniel Dimitrov, Philipp Sven Lars Schäfer, Elias Farr, Pablo Rodriguez-Mier, Sebastian Lobentanzer, Pau Badia-i-Mompel, Aurelien Dugourd, Jovan Tanevski, Ricardo Omar Ramirez Flores, Julio Saez-Rodriguez
Maintainer-email: Daniel Dimitrov <daniel.dimitrov@embl.de>
License: BSD 3-Clause License
License-File: LICENSE
Classifier: Programming Language :: Python :: 3 :: Only
Classifier: Programming Language :: Python :: 3.10
Classifier: Programming Language :: Python :: 3.11
Classifier: Programming Language :: Python :: 3.12
Classifier: Programming Language :: Python :: 3.13
Requires-Python: <3.14,>=3.10
Requires-Dist: anndata>=0.7.4
Requires-Dist: docrep>=0.3.1
Requires-Dist: mudata
Requires-Dist: numba
Requires-Dist: pandas
Requires-Dist: plotnine>=0.10.1
Requires-Dist: scanpy
Requires-Dist: session-info2
Requires-Dist: tqdm>=4.0
Provides-Extra: dev
Requires-Dist: bumpversion>=0.6.0; extra == 'dev'
Requires-Dist: highspy>=1.9.0; extra == 'dev'
Requires-Dist: pre-commit>=3.0.0; extra == 'dev'
Requires-Dist: pytest>=8.0; extra == 'dev'
Requires-Dist: twine>=4.0.2; extra == 'dev'
Provides-Extra: doc
Requires-Dist: docutils!=0.18.*,!=0.19.*,>=0.8; extra == 'doc'
Requires-Dist: ipykernel; extra == 'doc'
Requires-Dist: ipython; extra == 'doc'
Requires-Dist: myst-nb>=1.1; extra == 'doc'
Requires-Dist: pre-commit; extra == 'doc'
Requires-Dist: setuptools; extra == 'doc'
Requires-Dist: sphinx-autodoc-typehints; extra == 'doc'
Requires-Dist: sphinx-book-theme>=1; extra == 'doc'
Requires-Dist: sphinx-copybutton; extra == 'doc'
Requires-Dist: sphinx-tabs; extra == 'doc'
Requires-Dist: sphinx>=8.1; extra == 'doc'
Requires-Dist: sphinxcontrib-bibtex>=1; extra == 'doc'
Requires-Dist: sphinxext-opengraph; extra == 'doc'
Provides-Extra: extras
Requires-Dist: cell2cell; extra == 'extras'
Requires-Dist: corneto==0.9.1-alpha.6; extra == 'extras'
Requires-Dist: cvxpy-base>=1.6.1; extra == 'extras'
Requires-Dist: decoupler>=2.0.0; extra == 'extras'
Requires-Dist: gseapy>=1.1.0; extra == 'extras'
Requires-Dist: kneed>=0.7.0; extra == 'extras'
Requires-Dist: mofapy2>=0.7.0; extra == 'extras'
Requires-Dist: mofax; extra == 'extras'
Requires-Dist: muon; extra == 'extras'
Requires-Dist: omnipath>=1.0.6; extra == 'extras'
Requires-Dist: pydeseq2>=0.3.5; extra == 'extras'
Requires-Dist: pyscipopt>=5.2.1; extra == 'extras'
Requires-Dist: requests>=2.25.1; extra == 'extras'
Provides-Extra: test
Requires-Dist: coverage; extra == 'test'
Requires-Dist: pytest; extra == 'test'
